traktor/__init__.py
traktor/__main__.py
traktor/admin.py
traktor/config.py
traktor/errors.py
traktor/settings.py
traktor/version.py
traktor/commands/__init__.py
traktor/commands/db.py
traktor/commands/main.py
traktor/commands/project.py
traktor/commands/task.py
traktor/commands/timer.py
traktor/engine/__init__.py
traktor/engine/db_engine.py
traktor/engine/engine.py
traktor/engine/project_mixin.py
traktor/engine/task_mixin.py
traktor/engine/timer_mixin.py
traktor/migrations/0001_initial.py
traktor/migrations/0002_auto_20200820_1837.py
traktor/migrations/0003_user.py
traktor/migrations/0004_auto_20200823_1858.py
traktor/migrations/0005_add_user_to_project.py
traktor/migrations/0006_project_slug_unique_for_user.py
traktor/migrations/__init__.py
traktor/models/__init__.py
traktor/models/entry.py
traktor/models/project.py
traktor/models/report.py
traktor/models/signals.py
traktor/models/task.py
traktor/models/user.py
traktor-0.0.10.dist-info/AUTHORS
traktor-0.0.10.dist-info/LICENSE
traktor-0.0.10.dist-info/METADATA
traktor-0.0.10.dist-info/WHEEL
traktor-0.0.10.dist-info/entry_points.txt
traktor-0.0.10.dist-info/top_level.txt
traktor-0.0.10.dist-info/RECORD
