Metadata-Version: 2.1
Name: traktor
Version: 0.0.10
Summary: Python command line application for tracking time.
Home-page: https://github.com/alefnula/traktor
Author: Viktor Kerkez
Author-email: alefnula@gmail.com
Maintainer: Viktor Kerkez
Maintainer-email: alefnula@gmail.com
License: Apache-2.0
Platform: Windows
Platform: POSIX
Platform: MacOSX
Classifier: Programming Language :: Python :: 3
Classifier: Programming Language :: Python :: 3.7
Classifier: Programming Language :: Python :: 3.8
Classifier: License :: OSI Approved :: Apache Software License
Classifier: Operating System :: OS Independent
Requires-Dist: django (~=3.1.1)
Requires-Dist: ipython (~=7.18.1)
Requires-Dist: tea-console (~=0.0.5)
Requires-Dist: tea-django (~=0.0.11)
Requires-Dist: tea (~=0.1.2)
Requires-Dist: typer (~=0.3.2)
